archive/notes/pdoc.py
examples/list_ports.py
examples/Serial/asyncio/analog_input_sa.py
examples/Serial/asyncio/blink_sa.py
examples/Serial/asyncio/dht_sa.py
examples/Serial/asyncio/digital_input_pullup_sa.py
examples/Serial/asyncio/fade_sa.py
examples/Serial/asyncio/fade_with_range_sa.py
examples/Serial/asyncio/get_cpu_temperature_sa.py
examples/Serial/asyncio/get_pico_pins_sa.py
examples/Serial/asyncio/hc_sr04._sa.py
examples/Serial/asyncio/i2c_adxl345_accelerometer_sa.py
examples/Serial/asyncio/loop_back_sa.py
examples/Serial/asyncio/neopixels_aio_sa.py
examples/Serial/asyncio/servo_sa.py
examples/Serial/asyncio/spi_bme280_sa.py
examples/Serial/asyncio/stepper_absolute_sa.py
examples/Serial/asyncio/stepper_continuous_sa.py
examples/Serial/asyncio/stepper_relative_sa.py
examples/Serial/asyncio/stepper_run_speed_to_position_sa.py
examples/Serial/threaded/analog_input_st.py
examples/Serial/threaded/blink_st.py
examples/Serial/threaded/dht_st.py
examples/Serial/threaded/digital_input_pullup_st.py
examples/Serial/threaded/fade_st.py
examples/Serial/threaded/fade_with_range_st.py
examples/Serial/threaded/four_digital_pins.py
examples/Serial/threaded/get_cpu_temperature_st.py
examples/Serial/threaded/get_pico_pins_st.py
examples/Serial/threaded/hc_sr04._st.py
examples/Serial/threaded/i2c_adxl345_accelerometer_st.py
examples/Serial/threaded/loop_back_st.py
examples/Serial/threaded/neopixels_st.py
examples/Serial/threaded/servo_st.py
examples/Serial/threaded/spi_bme280_st.py
examples/Serial/threaded/stepper_absolute_st.py
examples/Serial/threaded/stepper_continuous_st.py
examples/Serial/threaded/stepper_relative_st.py
examples/Serial/threaded/stepper_run_speed_to_position_st.py
examples/WIFI/asyncio/analog_input_aio_wa.py
examples/WIFI/asyncio/blink_aio_wa.py
examples/WIFI/asyncio/dht_aio_wa.py
examples/WIFI/asyncio/digital_input_pullup_wa.py
examples/WIFI/asyncio/fade_wa.py
examples/WIFI/asyncio/fade_with_range_wa.py
examples/WIFI/asyncio/get_cpu_temperature_aio_wa.py
telemetrix_rpi_pico_2w-1.1.0.dist-info/METADATA
telemetrix_rpi_pico_2w-1.1.0.dist-info/WHEEL
telemetrix_rpi_pico_2w-1.1.0.dist-info/top_level.txt
telemetrix_rpi_pico_2w-1.1.0.dist-info/RECORD
