Metadata-Version: 2.4
Name: telemetrix-rpi-pico-2w
Version: 1.1.0
Summary: Telemetrix Client For the Raspberry Pi Pico-2W
Author-email: Alan Yorinks <MisterYsLab@gmail.com>
License: AGPL-3.0-or-later
Project-URL: Homepage, https://github.com/MrYsLab/telemetrix-rpi-pico-2w
Project-URL: Issues, https://github.com/MrYsLab/telemetrix-rpi-pico-2w/issues
Keywords: telemetrix,Raspberry Pi,Pico,Pico-w,Python
Classifier: Development Status :: 5 - Production/Stable
Classifier: Environment :: Other Environment
Classifier: Intended Audience :: Developers
Classifier: Intended Audience :: Education
Classifier: Operating System :: OS Independent
Classifier: Topic :: Software Development :: Libraries :: Python Modules
Requires-Python: >=3.10
Requires-Dist: pyserial
